dogstatsd_collector/__init__.py
dogstatsd_collector/base.py
dogstatsd_collector-0.0.1.dist-info/AUTHORS.rst
dogstatsd_collector-0.0.1.dist-info/LICENSE
dogstatsd_collector-0.0.1.dist-info/METADATA
dogstatsd_collector-0.0.1.dist-info/WHEEL
dogstatsd_collector-0.0.1.dist-info/top_level.txt
dogstatsd_collector-0.0.1.dist-info/RECORD
