Metadata-Version: 2.1
Name: dogstatsd-collector
Version: 0.0.1
Summary: A library to enable collection and delayed emission of StatsD metrics using the DataDog protocol.
Home-page: https://github.com/roverdotcom/dogstatsd-collector
Author: Alex Landau
Author-email: alex@rover.com
License: BSD 3-Clause License
Platform: UNKNOWN
Classifier: Development Status :: 4 - Beta
Classifier: Intended Audience :: Developers
Classifier: License :: OSI Approved :: BSD License
Classifier: Operating System :: Unix
Classifier: Operating System :: POSIX
Classifier: Operating System :: Microsoft :: Windows
Classifier: Programming Language :: Python
Classifier: Programming Language :: Python :: 2.7
Classifier: Programming Language :: Python :: 3
Classifier: Programming Language :: Python :: 3.5
Classifier: Programming Language :: Python :: 3.6
Classifier: Programming Language :: Python :: 3.7
Classifier: Topic :: Utilities
Requires-Dist: future
